uvify.py
uvify-0.1.7.dist-info/licenses/LICENSE
uvify-0.1.7.dist-info/METADATA
uvify-0.1.7.dist-info/WHEEL
uvify-0.1.7.dist-info/entry_points.txt
uvify-0.1.7.dist-info/top_level.txt
uvify-0.1.7.dist-info/RECORD
