Metadata-Version: 2.4
Name: uvify
Version: 0.1.7
Summary: Get one-liner commands for faster python environment uv python manager.
Author-email: Avi Lumelsky <avilum+gh@protonmail.com>
License: MIT License
Project-URL: homepage, https://github.com/avilum/uvify
Keywords: uv,python,environment,uvify,virtualenv,pip,poetry,venv
Requires-Python: >=3.10
License-File: LICENSE
Requires-Dist: gitingest>=0.1.5
Requires-Dist: toml>=0.10.2
Requires-Dist: typer>=0.12.3
Requires-Dist: rich>=13.7.1
Provides-Extra: api
Requires-Dist: fastapi>=0.111.0; extra == "api"
Requires-Dist: uvicorn>=0.29.0; extra == "api"
Dynamic: license-file
